jentry/__init__.py
jentry/config/__init__.py
jentry/config/meta.py
jentry/entry/__init__.py
jentry/entry/cli/__init__.py
jentry/entry/cli/cli.py
jentry/entry/cli/format.py
jentry/entry/cli/order.py
jentry/entry/script/__init__.py
jentry/entry/script/file.py
jentry/entry/script/project.py
jentry/model/__init__.py
jentry/model/entry.py
jentry-1.0.1.dist-info/LICENSE
jentry-1.0.1.dist-info/METADATA
jentry-1.0.1.dist-info/WHEEL
jentry-1.0.1.dist-info/entry_points.txt
jentry-1.0.1.dist-info/top_level.txt
jentry-1.0.1.dist-info/RECORD
