Metadata-Version: 2.1
Name: jentry
Version: 1.0.1
Summary: Python CLI which can find the entry of java project.
Home-page: https://github.com/hansbug/jentry
Author: HansBug
Author-email: hansbug@buaa.edu.cn
License: Apache License, Version 2.0
Keywords: Python CLI which can find the entry of java project.
Platform: UNKNOWN
Classifier: Development Status :: 5 - Production/Stable
Classifier: Intended Audience :: Developers
Classifier: License :: OSI Approved :: Apache Software License
Classifier: Programming Language :: Python
Classifier: Programming Language :: Python :: 3
Classifier: Programming Language :: Python :: 3.6
Classifier: Programming Language :: Python :: 3.7
Classifier: Programming Language :: Python :: 3.8
Classifier: Programming Language :: Python :: 3.9
Classifier: Programming Language :: Python :: 3.10
Requires-Python: >=3.6
License-File: LICENSE
Requires-Dist: click (>=7.1.0)
Requires-Dist: hbutils (>=0.2.0)
Requires-Dist: enum-tools (>=0.8.0)
Requires-Dist: javalang (>=0.13.0)
Requires-Dist: prettytable (>=2.5.0)
Provides-Extra: build
Requires-Dist: pyinstaller (<5,>=4.7) ; extra == 'build'
Provides-Extra: doc
Requires-Dist: sphinx (~=3.2.0) ; extra == 'doc'
Requires-Dist: sphinx-rtd-theme (~=0.4.3) ; extra == 'doc'
Requires-Dist: enum-tools ; extra == 'doc'
Requires-Dist: sphinx-toolbox ; extra == 'doc'
Requires-Dist: plantumlcli (>=0.0.4) ; extra == 'doc'
Requires-Dist: packaging ; extra == 'doc'
Requires-Dist: sphinx-multiversion (~=0.2.4) ; extra == 'doc'
Requires-Dist: where (~=1.0.2) ; extra == 'doc'
Requires-Dist: easydict (<2,>=1.7) ; extra == 'doc'
Requires-Dist: pyinstaller (<5,>=4.7) ; extra == 'doc'
Provides-Extra: test
Requires-Dist: coverage (>=5) ; extra == 'test'
Requires-Dist: pytest (~=6.2.5) ; extra == 'test'
Requires-Dist: pytest-cov (~=3.0.0) ; extra == 'test'
Requires-Dist: pytest-mock (~=3.6.1) ; extra == 'test'
Requires-Dist: pytest-rerunfailures (~=10.2) ; extra == 'test'
Requires-Dist: pytest-timeout (~=2.0.2) ; extra == 'test'
